[{"id":0,"name":"Boris","age":20},{"id":1,"name":"Dmitrii","age":36},{"id":2,"name":"Peter","age":36},{"id":3,"name":"Peter","age":42},{"id":4,"name":"Ivan","age":36},{"id":5,"name":"Peter","age":18},{"id":6,"name":"Dmitrii","age":27},{"id":7,"name":"Boris","age":25},{"id":8,"name":"Ivan","age":21},{"id":9,"name":"Dmitrii","age":26},{"id":10,"name":"Boris","age":22},{"id":11,"name":"Gleb","age":40},{"id":12,"name":"Peter","age":33},{"id":13,"name":"Ivan","age":45},{"id":14,"name":"Boris","age":28},{"id":15,"name":"Boris","age":19},{"id":16,"name":"Ivan","age":26},{"id":17,"name":"Dmitrii","age":28},{"id":18,"name":"Boris","age":25},{"id":19,"name":"Peter","age":42},{"id":20,"name":"Peter","age":18},{"id":21,"name":"Ivan","age":43},{"id":22,"name":"Ivan","age":32},{"id":23,"name":"Boris","age":34},{"id":24,"name":"Ivan","age":36},{"id":25,"name":"Gleb","age":32},{"id":26,"name":"Boris","age":45},{"id":27,"name":"Gleb","age":26},{"id":28,"name":"Boris","age":38},{"id":29,"name":"Peter","age":30},{"id":30,"name":"Boris","age":40},{"id":31,"name":"Gleb","age":26},{"id":32,"name":"Gleb","age":36},{"id":33,"name":"Dmitrii","age":36},{"id":34,"name":"Ivan","age":28},{"id":35,"name":"Gleb","age":23},{"id":36,"name":"Ivan","age":35},{"id":37,"name":"Gleb","age":39},{"id":38,"name":"Gleb","age":23},{"id":39,"name":"Ivan","age":24},{"id":40,"name":"Ivan","age":25},{"id":41,"name":"Peter","age":39},{"id":42,"name":"Boris","age":34},{"id":43,"name":"Boris","age":42},{"id":44,"name":"Gleb","age":36},{"id":45,"name":"Peter","age":24},{"id":46,"name":"Peter","age":19},{"id":47,"name":"Gleb","age":19},{"id":48,"name":"Gleb","age":32},{"id":49,"name":"Gleb","age":36}]